{
  "stats": {
    "suites": 4,
    "tests": 46,
    "passes": 45,
    "pending": 0,
    "failures": 1,
    "start": "2023-06-27T10:14:15.030Z",
    "end": "2023-06-27T10:19:48.175Z",
    "duration": 291828,
    "testsRegistered": 46,
    "passPercent": 97.82608695652173,
    "pendingPercent": 0,
    "other": 0,
    "hasOther": false,
    "skipped": 0,
    "hasSkipped": false
  },
  "results": [
    {
      "uuid": "a1e6e3b3-2fc9-4774-86bb-726b2bbff425",
      "title": "",
      "fullFile": "cypress\\e2e\\eva-md\\manager-admin\\newsfeed.ts",
      "file": "cypress\\e2e\\eva-md\\manager-admin\\newsfeed.ts",
      "beforeHooks": [],
      "afterHooks": [],
      "tests": [],
      "suites": [
        {
          "uuid": "9beb3c05-567c-4519-9f37-763948362bbf",
          "title": "EVA MD : Newsfeed - Manager Admin",
          "fullFile": "",
          "file": "",
          "beforeHooks": [],
          "afterHooks": [],
          "tests": [
            {
              "title": "Default items should visible",
              "fullTitle": "EVA MD : Newsfeed - Manager Admin Default items should visible",
              "timedOut": null,
              "duration": 29609,
              "state": "passed",
              "speed": "slow",
              "pass": true,
              "fail": false,
              "pending": false,
              "context": null,
              "code": "NEWS_FEED.verifyItemsIfExist('MA');\nFOOTER.verifyItemsIfExist('EVA_MD');\nHEADER.verifyItemsIfExist('MA');",
              "err": {},
              "uuid": "a9834aab-699e-4831-9a3a-05ed6fd48f94",
              "parentUUID": "9beb3c05-567c-4519-9f37-763948362bbf",
              "isHook": false,
              "skipped": false
            },
            {
              "title": "Check texts/labels if visible",
              "fullTitle": "EVA MD : Newsfeed - Manager Admin Check texts/labels if visible",
              "timedOut": null,
              "duration": 3522,
              "state": "passed",
              "speed": "fast",
              "pass": true,
              "fail": false,
              "pending": false,
              "context": null,
              "code": "NEWS_FEED.verifyTextsIfContains('MA');\nFOOTER.verifyTextsIfContains('', 'EVA_MD');\nHEADER.verifyTextsIfContains();",
              "err": {},
              "uuid": "a3a2d14d-8646-4c71-8229-a1dbcb9a70af",
              "parentUUID": "9beb3c05-567c-4519-9f37-763948362bbf",
              "isHook": false,
              "skipped": false
            },
            {
              "title": "Validate Notifications",
              "fullTitle": "EVA MD : Newsfeed - Manager Admin Validate Notifications",
              "timedOut": null,
              "duration": 14789,
              "state": "passed",
              "speed": "slow",
              "pass": true,
              "fail": false,
              "pending": false,
              "context": null,
              "code": "NEWS_FEED.notifications('MA');\nCOMM_ELEMENTS.hideLoadingScreen();",
              "err": {},
              "uuid": "7c114497-cb3d-4c2c-b7bd-c3b1a6d1c717",
              "parentUUID": "9beb3c05-567c-4519-9f37-763948362bbf",
              "isHook": false,
              "skipped": false
            },
            {
              "title": "Validate Advanced Filters",
              "fullTitle": "EVA MD : Newsfeed - Manager Admin Validate Advanced Filters",
              "timedOut": null,
              "duration": 15336,
              "state": "passed",
              "speed": "slow",
              "pass": true,
              "fail": false,
              "pending": false,
              "context": null,
              "code": "NEWS_FEED.advancedFilters();",
              "err": {},
              "uuid": "bc87a7fc-f982-4024-b095-9ab47a2e833a",
              "parentUUID": "9beb3c05-567c-4519-9f37-763948362bbf",
              "isHook": false,
              "skipped": false
            },
            {
              "title": "Validate Sortings",
              "fullTitle": "EVA MD : Newsfeed - Manager Admin Validate Sortings",
              "timedOut": null,
              "duration": 8818,
              "state": "passed",
              "speed": "medium",
              "pass": true,
              "fail": false,
              "pending": false,
              "context": null,
              "code": "NEWS_FEED.sortBy();",
              "err": {},
              "uuid": "8d1bf44e-6a2c-4f7f-9248-69ff84ae5a54",
              "parentUUID": "9beb3c05-567c-4519-9f37-763948362bbf",
              "isHook": false,
              "skipped": false
            },
            {
              "title": "Validate Search by Hasthag",
              "fullTitle": "EVA MD : Newsfeed - Manager Admin Validate Search by Hasthag",
              "timedOut": null,
              "duration": 5976,
              "state": "passed",
              "speed": "medium",
              "pass": true,
              "fail": false,
              "pending": false,
              "context": null,
              "code": "NEWS_FEED.searchBy('hashtag');",
              "err": {},
              "uuid": "e4b86705-d296-4519-aee7-f9cb93b21714",
              "parentUUID": "9beb3c05-567c-4519-9f37-763948362bbf",
              "isHook": false,
              "skipped": false
            },
            {
              "title": "Validate Search by Users",
              "fullTitle": "EVA MD : Newsfeed - Manager Admin Validate Search by Users",
              "timedOut": null,
              "duration": 5358,
              "state": "passed",
              "speed": "medium",
              "pass": true,
              "fail": false,
              "pending": false,
              "context": null,
              "code": "NEWS_FEED.searchBy('user');",
              "err": {},
              "uuid": "3127b633-3a4d-4e6c-8cef-05fa6cd047e7",
              "parentUUID": "9beb3c05-567c-4519-9f37-763948362bbf",
              "isHook": false,
              "skipped": false
            },
            {
              "title": "Negative - Validate MA/M/E (non-internal bpp) does not have authorized to publish a post",
              "fullTitle": "EVA MD : Newsfeed - Manager Admin Negative - Validate MA/M/E (non-internal bpp) does not have authorized to publish a post",
              "timedOut": null,
              "duration": 3592,
              "state": "passed",
              "speed": "fast",
              "pass": true,
              "fail": false,
              "pending": false,
              "context": null,
              "code": "NEWS_FEED.verifyItemsIfExist('MA');",
              "err": {},
              "uuid": "8a8af7cd-898f-4f0f-8c66-ea3a66414c93",
              "parentUUID": "9beb3c05-567c-4519-9f37-763948362bbf",
              "isHook": false,
              "skipped": false
            },
            {
              "title": "Edge - Validate Press ENTER key on keyboard on Newsfeed Screen",
              "fullTitle": "EVA MD : Newsfeed - Manager Admin Edge - Validate Press ENTER key on keyboard on Newsfeed Screen",
              "timedOut": null,
              "duration": 3381,
              "state": "passed",
              "speed": "fast",
              "pass": true,
              "fail": false,
              "pending": false,
              "context": null,
              "code": "cy.get(\"body\").type(\"{enter}\");\nNEWS_FEED.verifyItemsIfExist('MA');",
              "err": {},
              "uuid": "1bbd2a34-c4c7-4ba5-b0fd-d6483ecf822f",
              "parentUUID": "9beb3c05-567c-4519-9f37-763948362bbf",
              "isHook": false,
              "skipped": false
            },
            {
              "title": "Negative - Validate search on non existing user",
              "fullTitle": "EVA MD : Newsfeed - Manager Admin Negative - Validate search on non existing user",
              "timedOut": null,
              "duration": 7036,
              "state": "passed",
              "speed": "medium",
              "pass": true,
              "fail": false,
              "pending": false,
              "context": null,
              "code": "NEWS_FEED.unregisteredUserHashtag('user');",
              "err": {},
              "uuid": "e5275bb8-c36a-4061-a651-a966c3589639",
              "parentUUID": "9beb3c05-567c-4519-9f37-763948362bbf",
              "isHook": false,
              "skipped": false
            },
            {
              "title": "Negative - Validate search on non existing hashtags",
              "fullTitle": "EVA MD : Newsfeed - Manager Admin Negative - Validate search on non existing hashtags",
              "timedOut": null,
              "duration": 7493,
              "state": "passed",
              "speed": "medium",
              "pass": true,
              "fail": false,
              "pending": false,
              "context": null,
              "code": "NEWS_FEED.unregisteredUserHashtag('hashtag');",
              "err": {},
              "uuid": "5fd7c8ab-d27d-480e-ae00-dd194d2c22c6",
              "parentUUID": "9beb3c05-567c-4519-9f37-763948362bbf",
              "isHook": false,
              "skipped": false
            }
          ],
          "suites": [],
          "passes": [
            "a9834aab-699e-4831-9a3a-05ed6fd48f94",
            "a3a2d14d-8646-4c71-8229-a1dbcb9a70af",
            "7c114497-cb3d-4c2c-b7bd-c3b1a6d1c717",
            "bc87a7fc-f982-4024-b095-9ab47a2e833a",
            "8d1bf44e-6a2c-4f7f-9248-69ff84ae5a54",
            "e4b86705-d296-4519-aee7-f9cb93b21714",
            "3127b633-3a4d-4e6c-8cef-05fa6cd047e7",
            "8a8af7cd-898f-4f0f-8c66-ea3a66414c93",
            "1bbd2a34-c4c7-4ba5-b0fd-d6483ecf822f",
            "e5275bb8-c36a-4061-a651-a966c3589639",
            "5fd7c8ab-d27d-480e-ae00-dd194d2c22c6"
          ],
          "failures": [],
          "pending": [],
          "skipped": [],
          "duration": 104910,
          "root": false,
          "rootEmpty": false,
          "_timeout": 2000
        }
      ],
      "passes": [],
      "failures": [],
      "pending": [],
      "skipped": [],
      "duration": 0,
      "root": true,
      "rootEmpty": true,
      "_timeout": 2000
    },
    {
      "uuid": "ea4d8e3e-3fa4-4f02-9d4d-5bd471e7b895",
      "title": "",
      "fullFile": "cypress\\e2e\\eva-md\\manager-admin\\profile.ts",
      "file": "cypress\\e2e\\eva-md\\manager-admin\\profile.ts",
      "beforeHooks": [],
      "afterHooks": [],
      "tests": [],
      "suites": [
        {
          "uuid": "eaa1eab7-9944-4f44-8374-e7cacda48d2b",
          "title": "EVA MD : General - Manager Admin",
          "fullFile": "",
          "file": "",
          "beforeHooks": [],
          "afterHooks": [],
          "tests": [
            {
              "title": "Application Menu : Default items should visible",
              "fullTitle": "EVA MD : General - Manager Admin Application Menu : Default items should visible",
              "timedOut": null,
              "duration": 31527,
              "state": "passed",
              "speed": "slow",
              "pass": true,
              "fail": false,
              "pending": false,
              "context": null,
              "code": "cy.loginPortal();\nSIDE_NAV_BAR.basePoint();\nSIDE_NAV_BAR.verifyItemsIfExist('MA');",
              "err": {},
              "uuid": "3ba8b938-aa79-4354-b396-1099d7773b93",
              "parentUUID": "eaa1eab7-9944-4f44-8374-e7cacda48d2b",
              "isHook": false,
              "skipped": false
            },
            {
              "title": "Application Menu : Check texts/labels if visible",
              "fullTitle": "EVA MD : General - Manager Admin Application Menu : Check texts/labels if visible",
              "timedOut": null,
              "duration": 36,
              "state": "passed",
              "speed": "fast",
              "pass": true,
              "fail": false,
              "pending": false,
              "context": null,
              "code": "SIDE_NAV_BAR.verifyTextsIfContains('MA');",
              "err": {},
              "uuid": "329cc167-d093-490e-8fc2-c73441fc2fc3",
              "parentUUID": "eaa1eab7-9944-4f44-8374-e7cacda48d2b",
              "isHook": false,
              "skipped": false
            },
            {
              "title": "Application Menu : Validate favorite application",
              "fullTitle": "EVA MD : General - Manager Admin Application Menu : Validate favorite application",
              "timedOut": null,
              "duration": 15940,
              "state": "passed",
              "speed": "slow",
              "pass": true,
              "fail": false,
              "pending": false,
              "context": null,
              "code": "SIDE_NAV_BAR.favoriteApp();\nCOMM_ELEMENTS.toasterFavApp();",
              "err": {},
              "uuid": "6a79bcf1-ff92-44a7-b190-f7b6e7046bc4",
              "parentUUID": "eaa1eab7-9944-4f44-8374-e7cacda48d2b",
              "isHook": false,
              "skipped": false
            },
            {
              "title": "My Profile : Default items and fields should visible",
              "fullTitle": "EVA MD : General - Manager Admin My Profile : Default items and fields should visible",
              "timedOut": null,
              "duration": 3559,
              "state": "passed",
              "speed": "fast",
              "pass": true,
              "fail": false,
              "pending": false,
              "context": null,
              "code": "SIDE_NAV_BAR.editProfile();\nMY_PROFILE.verifyItemsIfExist('EVA_MD', 'MA');\nFOOTER.verifyItemsIfExist('EVA_MD');\nHEADER.verifyItemsIfExist('MA');",
              "err": {},
              "uuid": "0e0be5a6-efa1-4acd-85a6-bc25f41613da",
              "parentUUID": "eaa1eab7-9944-4f44-8374-e7cacda48d2b",
              "isHook": false,
              "skipped": false
            },
            {
              "title": "My Profile : Check texts/labels if visible",
              "fullTitle": "EVA MD : General - Manager Admin My Profile : Check texts/labels if visible",
              "timedOut": null,
              "duration": 239,
              "state": "passed",
              "speed": "fast",
              "pass": true,
              "fail": false,
              "pending": false,
              "context": null,
              "code": "MY_PROFILE.verifyTextsIfContains('MA');\nFOOTER.verifyTextsIfContains('', 'EVA_MD');\nHEADER.verifyTextsIfContains();",
              "err": {},
              "uuid": "02a65948-7f71-4edc-8e46-a2e9a97aebb8",
              "parentUUID": "eaa1eab7-9944-4f44-8374-e7cacda48d2b",
              "isHook": false,
              "skipped": false
            },
            {
              "title": "My Profile : Update Basic Information",
              "fullTitle": "EVA MD : General - Manager Admin My Profile : Update Basic Information",
              "timedOut": null,
              "duration": 17792,
              "state": "failed",
              "speed": null,
              "pass": false,
              "fail": true,
              "pending": false,
              "context": null,
              "code": "MY_PROFILE.profile('update_basic_info');\nCOMM_ELEMENTS.toaster('success');\ncy.reload();",
              "err": {
                "message": "AssertionError: expected undefined to be true",
                "estack": "AssertionError: expected undefined to be true\n    at Context.eval (webpack:///./cypress/page-objects/internal-bpp/partner-admin/my_profile.ts:206:71)",
                "diff": null
              },
              "uuid": "7a2a4516-29bf-495d-b1d3-b68c66d44d3c",
              "parentUUID": "eaa1eab7-9944-4f44-8374-e7cacda48d2b",
              "isHook": false,
              "skipped": false
            },
            {
              "title": "My Profile (NEGATIVE) : Invalidate Update button with empty mandatory fields",
              "fullTitle": "EVA MD : General - Manager Admin My Profile (NEGATIVE) : Invalidate Update button with empty mandatory fields",
              "timedOut": null,
              "duration": 4153,
              "state": "passed",
              "speed": "fast",
              "pass": true,
              "fail": false,
              "pending": false,
              "context": null,
              "code": "MY_PROFILE.profile('clear_all_fields');\ncy.reload();",
              "err": {},
              "uuid": "63786a4b-5c50-44ee-95c0-d973194f3900",
              "parentUUID": "eaa1eab7-9944-4f44-8374-e7cacda48d2b",
              "isHook": false,
              "skipped": false
            },
            {
              "title": "My Profile (NEGATIVE) : Password and verify fields password does not match",
              "fullTitle": "EVA MD : General - Manager Admin My Profile (NEGATIVE) : Password and verify fields password does not match",
              "timedOut": null,
              "duration": 6419,
              "state": "passed",
              "speed": "medium",
              "pass": true,
              "fail": false,
              "pending": false,
              "context": null,
              "code": "MY_PROFILE.profile('un_matched_password');\ncy.reload();",
              "err": {},
              "uuid": "48460348-cb2d-4cee-875f-80d6094fc6d9",
              "parentUUID": "eaa1eab7-9944-4f44-8374-e7cacda48d2b",
              "isHook": false,
              "skipped": false
            },
            {
              "title": "My Profile (NEGATIVE) : Enter a screen name that has special characters",
              "fullTitle": "EVA MD : General - Manager Admin My Profile (NEGATIVE) : Enter a screen name that has special characters",
              "timedOut": null,
              "duration": 3954,
              "state": "passed",
              "speed": "fast",
              "pass": true,
              "fail": false,
              "pending": false,
              "context": null,
              "code": "MY_PROFILE.profile('validate_screen_name');",
              "err": {},
              "uuid": "165da9d6-621d-4663-8a84-31de8de43052",
              "parentUUID": "eaa1eab7-9944-4f44-8374-e7cacda48d2b",
              "isHook": false,
              "skipped": false
            },
            {
              "title": "My Profile (EDGE CASE) : Add alphabet and special character on phone number",
              "fullTitle": "EVA MD : General - Manager Admin My Profile (EDGE CASE) : Add alphabet and special character on phone number",
              "timedOut": null,
              "duration": 491,
              "state": "passed",
              "speed": "fast",
              "pass": true,
              "fail": false,
              "pending": false,
              "context": null,
              "code": "MY_PROFILE.profile('validate_phone_number');",
              "err": {},
              "uuid": "32379cbe-a0a1-422a-9891-4b60d5528d8c",
              "parentUUID": "eaa1eab7-9944-4f44-8374-e7cacda48d2b",
              "isHook": false,
              "skipped": false
            },
            {
              "title": "My Profile (EDGE CASE) : Add alphabet and special character on mobile number",
              "fullTitle": "EVA MD : General - Manager Admin My Profile (EDGE CASE) : Add alphabet and special character on mobile number",
              "timedOut": null,
              "duration": 506,
              "state": "passed",
              "speed": "fast",
              "pass": true,
              "fail": false,
              "pending": false,
              "context": null,
              "code": "MY_PROFILE.profile('validate_mobile_number');",
              "err": {},
              "uuid": "e79d0923-18b1-40fe-a5a5-9d16907c7c4a",
              "parentUUID": "eaa1eab7-9944-4f44-8374-e7cacda48d2b",
              "isHook": false,
              "skipped": false
            },
            {
              "title": "My Profile (OOTB) : Able to change country code on phone number",
              "fullTitle": "EVA MD : General - Manager Admin My Profile (OOTB) : Able to change country code on phone number",
              "timedOut": null,
              "duration": 3526,
              "state": "passed",
              "speed": "fast",
              "pass": true,
              "fail": false,
              "pending": false,
              "context": null,
              "code": "MY_PROFILE.profile('validate_mobile_country_code');\ncy.reload();",
              "err": {},
              "uuid": "7e84fdba-7a98-4e6a-a707-23d7a02ea7ce",
              "parentUUID": "eaa1eab7-9944-4f44-8374-e7cacda48d2b",
              "isHook": false,
              "skipped": false
            },
            {
              "title": "My Profile (OOTB) : Enter a screen name with spaces only",
              "fullTitle": "EVA MD : General - Manager Admin My Profile (OOTB) : Enter a screen name with spaces only",
              "timedOut": null,
              "duration": 3344,
              "state": "passed",
              "speed": "fast",
              "pass": true,
              "fail": false,
              "pending": false,
              "context": null,
              "code": "MY_PROFILE.profile('validate_screen_name_with_spaces');",
              "err": {},
              "uuid": "ebf7bdd5-fbf8-44a9-bd76-e40fb9215022",
              "parentUUID": "eaa1eab7-9944-4f44-8374-e7cacda48d2b",
              "isHook": false,
              "skipped": false
            },
            {
              "title": "My Profile (OOTB) : Disable update button when mandatory fields are empty",
              "fullTitle": "EVA MD : General - Manager Admin My Profile (OOTB) : Disable update button when mandatory fields are empty",
              "timedOut": null,
              "duration": 579,
              "state": "passed",
              "speed": "fast",
              "pass": true,
              "fail": false,
              "pending": false,
              "context": null,
              "code": "MY_PROFILE.profile('disable_update_button');",
              "err": {},
              "uuid": "e5359f74-368c-4cef-b6f4-d9818486a667",
              "parentUUID": "eaa1eab7-9944-4f44-8374-e7cacda48d2b",
              "isHook": false,
              "skipped": false
            },
            {
              "title": "My Profile : Validate Password Strength - risk",
              "fullTitle": "EVA MD : General - Manager Admin My Profile : Validate Password Strength - risk",
              "timedOut": null,
              "duration": 617,
              "state": "passed",
              "speed": "fast",
              "pass": true,
              "fail": false,
              "pending": false,
              "context": null,
              "code": "COMM_ELEMENTS.passwordStrength('risky');",
              "err": {},
              "uuid": "5d687251-aa30-4144-a854-10501f509cf5",
              "parentUUID": "eaa1eab7-9944-4f44-8374-e7cacda48d2b",
              "isHook": false,
              "skipped": false
            },
            {
              "title": "My Profile : Validate Password Strength - weak",
              "fullTitle": "EVA MD : General - Manager Admin My Profile : Validate Password Strength - weak",
              "timedOut": null,
              "duration": 668,
              "state": "passed",
              "speed": "fast",
              "pass": true,
              "fail": false,
              "pending": false,
              "context": null,
              "code": "COMM_ELEMENTS.passwordStrength('weak');",
              "err": {},
              "uuid": "99d97ed8-2dac-4c8a-974e-efbaf259ae42",
              "parentUUID": "eaa1eab7-9944-4f44-8374-e7cacda48d2b",
              "isHook": false,
              "skipped": false
            },
            {
              "title": "My Profile : Validate Password Strength - fair",
              "fullTitle": "EVA MD : General - Manager Admin My Profile : Validate Password Strength - fair",
              "timedOut": null,
              "duration": 1202,
              "state": "passed",
              "speed": "fast",
              "pass": true,
              "fail": false,
              "pending": false,
              "context": null,
              "code": "COMM_ELEMENTS.passwordStrength('fair');",
              "err": {},
              "uuid": "0d1670d9-e37f-4afe-b8ac-2d605d516266",
              "parentUUID": "eaa1eab7-9944-4f44-8374-e7cacda48d2b",
              "isHook": false,
              "skipped": false
            },
            {
              "title": "Validate Password Strength - good",
              "fullTitle": "EVA MD : General - Manager Admin Validate Password Strength - good",
              "timedOut": null,
              "duration": 754,
              "state": "passed",
              "speed": "fast",
              "pass": true,
              "fail": false,
              "pending": false,
              "context": null,
              "code": "COMM_ELEMENTS.passwordStrength('good');",
              "err": {},
              "uuid": "d0992034-7cfb-42d9-b7fa-d3066757adf4",
              "parentUUID": "eaa1eab7-9944-4f44-8374-e7cacda48d2b",
              "isHook": false,
              "skipped": false
            },
            {
              "title": "My Profile : Validate Password Strength - strong",
              "fullTitle": "EVA MD : General - Manager Admin My Profile : Validate Password Strength - strong",
              "timedOut": null,
              "duration": 1035,
              "state": "passed",
              "speed": "fast",
              "pass": true,
              "fail": false,
              "pending": false,
              "context": null,
              "code": "COMM_ELEMENTS.passwordStrength('strong');",
              "err": {},
              "uuid": "d14a58af-5b1a-4b09-a1cf-f756bc7d1cae",
              "parentUUID": "eaa1eab7-9944-4f44-8374-e7cacda48d2b",
              "isHook": false,
              "skipped": false
            }
          ],
          "suites": [],
          "passes": [
            "3ba8b938-aa79-4354-b396-1099d7773b93",
            "329cc167-d093-490e-8fc2-c73441fc2fc3",
            "6a79bcf1-ff92-44a7-b190-f7b6e7046bc4",
            "0e0be5a6-efa1-4acd-85a6-bc25f41613da",
            "02a65948-7f71-4edc-8e46-a2e9a97aebb8",
            "63786a4b-5c50-44ee-95c0-d973194f3900",
            "48460348-cb2d-4cee-875f-80d6094fc6d9",
            "165da9d6-621d-4663-8a84-31de8de43052",
            "32379cbe-a0a1-422a-9891-4b60d5528d8c",
            "e79d0923-18b1-40fe-a5a5-9d16907c7c4a",
            "7e84fdba-7a98-4e6a-a707-23d7a02ea7ce",
            "ebf7bdd5-fbf8-44a9-bd76-e40fb9215022",
            "e5359f74-368c-4cef-b6f4-d9818486a667",
            "5d687251-aa30-4144-a854-10501f509cf5",
            "99d97ed8-2dac-4c8a-974e-efbaf259ae42",
            "0d1670d9-e37f-4afe-b8ac-2d605d516266",
            "d0992034-7cfb-42d9-b7fa-d3066757adf4",
            "d14a58af-5b1a-4b09-a1cf-f756bc7d1cae"
          ],
          "failures": [
            "7a2a4516-29bf-495d-b1d3-b68c66d44d3c"
          ],
          "pending": [],
          "skipped": [],
          "duration": 96341,
          "root": false,
          "rootEmpty": false,
          "_timeout": 2000
        }
      ],
      "passes": [],
      "failures": [],
      "pending": [],
      "skipped": [],
      "duration": 0,
      "root": true,
      "rootEmpty": true,
      "_timeout": 2000
    },
    {
      "uuid": "645d9367-91f2-4618-8a5d-8e563a02ee3a",
      "title": "",
      "fullFile": "cypress\\e2e\\eva-md\\manager-admin\\reg_codes.ts",
      "file": "cypress\\e2e\\eva-md\\manager-admin\\reg_codes.ts",
      "beforeHooks": [],
      "afterHooks": [],
      "tests": [],
      "suites": [
        {
          "uuid": "eed1b4cd-40a8-4389-a607-4b0bd1e0baf7",
          "title": "EVA MD : Add New Managers - Registration codes",
          "fullFile": "",
          "file": "",
          "beforeHooks": [],
          "afterHooks": [],
          "tests": [
            {
              "title": "Default items should visible",
              "fullTitle": "EVA MD : Add New Managers - Registration codes Default items should visible",
              "timedOut": null,
              "duration": 3567,
              "state": "passed",
              "speed": "fast",
              "pass": true,
              "fail": false,
              "pending": false,
              "context": null,
              "code": "NEW_USER.register('default_items', null);",
              "err": {},
              "uuid": "eb7b6d80-1ab4-47a6-b8a1-1c4686dd2226",
              "parentUUID": "eed1b4cd-40a8-4389-a607-4b0bd1e0baf7",
              "isHook": false,
              "skipped": false
            },
            {
              "title": "Validate successful new user account creation",
              "fullTitle": "EVA MD : Add New Managers - Registration codes Validate successful new user account creation",
              "timedOut": null,
              "duration": 11107,
              "state": "passed",
              "speed": "slow",
              "pass": true,
              "fail": false,
              "pending": false,
              "context": null,
              "code": "NEW_USER.register('add_user', 'success_creation');",
              "err": {},
              "uuid": "18ad9a9b-c89a-46ec-b172-ead449a188e3",
              "parentUUID": "eed1b4cd-40a8-4389-a607-4b0bd1e0baf7",
              "isHook": false,
              "skipped": false
            },
            {
              "title": "Validate existing user",
              "fullTitle": "EVA MD : Add New Managers - Registration codes Validate existing user",
              "timedOut": null,
              "duration": 8308,
              "state": "passed",
              "speed": "medium",
              "pass": true,
              "fail": false,
              "pending": false,
              "context": null,
              "code": "NEW_USER.register('add_user', 'already_exist');",
              "err": {},
              "uuid": "0883a395-3abd-4b6d-b2b6-c6fd7d85f3da",
              "parentUUID": "eed1b4cd-40a8-4389-a607-4b0bd1e0baf7",
              "isHook": false,
              "skipped": false
            },
            {
              "title": "Validate existing user",
              "fullTitle": "EVA MD : Add New Managers - Registration codes Validate existing user",
              "timedOut": null,
              "duration": 323,
              "state": "passed",
              "speed": "fast",
              "pass": true,
              "fail": false,
              "pending": false,
              "context": null,
              "code": "NEW_USER.register('cancel_creating_user', null);",
              "err": {},
              "uuid": "fa6c5de4-2de0-4628-abac-7f746d4d5689",
              "parentUUID": "eed1b4cd-40a8-4389-a607-4b0bd1e0baf7",
              "isHook": false,
              "skipped": false
            },
            {
              "title": "Check field validations",
              "fullTitle": "EVA MD : Add New Managers - Registration codes Check field validations",
              "timedOut": null,
              "duration": 2064,
              "state": "passed",
              "speed": "fast",
              "pass": true,
              "fail": false,
              "pending": false,
              "context": null,
              "code": "NEW_USER.register('disable_submit_button', null);",
              "err": {},
              "uuid": "7763df55-e9d8-48e0-a153-e3d4642e053f",
              "parentUUID": "eed1b4cd-40a8-4389-a607-4b0bd1e0baf7",
              "isHook": false,
              "skipped": false
            },
            {
              "title": "Validate matching email and confirm email fields",
              "fullTitle": "EVA MD : Add New Managers - Registration codes Validate matching email and confirm email fields",
              "timedOut": null,
              "duration": 7041,
              "state": "passed",
              "speed": "medium",
              "pass": true,
              "fail": false,
              "pending": false,
              "context": null,
              "code": "NEW_USER.register('validation_fields', 'email_not_matched');",
              "err": {},
              "uuid": "b463a845-3203-45d5-95df-42cc0da719cc",
              "parentUUID": "eed1b4cd-40a8-4389-a607-4b0bd1e0baf7",
              "isHook": false,
              "skipped": false
            },
            {
              "title": "Validate matching password and verify password fields",
              "fullTitle": "EVA MD : Add New Managers - Registration codes Validate matching password and verify password fields",
              "timedOut": null,
              "duration": 7341,
              "state": "passed",
              "speed": "medium",
              "pass": true,
              "fail": false,
              "pending": false,
              "context": null,
              "code": "NEW_USER.register('validation_fields', 'passwords_not_matched');",
              "err": {},
              "uuid": "c6661eb8-b05e-49c8-a4b3-21c70b1450b8",
              "parentUUID": "eed1b4cd-40a8-4389-a607-4b0bd1e0baf7",
              "isHook": false,
              "skipped": false
            },
            {
              "title": "Create account : Validate Password Strength - risk",
              "fullTitle": "EVA MD : Add New Managers - Registration codes Create account : Validate Password Strength - risk",
              "timedOut": null,
              "duration": 666,
              "state": "passed",
              "speed": "fast",
              "pass": true,
              "fail": false,
              "pending": false,
              "context": null,
              "code": "NEW_USER.newUser.click();\nCOMM_ELEMENTS.passwordStrength('risky');",
              "err": {},
              "uuid": "d20bd169-083f-45e3-867b-6fc2ca17604a",
              "parentUUID": "eed1b4cd-40a8-4389-a607-4b0bd1e0baf7",
              "isHook": false,
              "skipped": false
            },
            {
              "title": "Create account : Validate Password Strength - weak",
              "fullTitle": "EVA MD : Add New Managers - Registration codes Create account : Validate Password Strength - weak",
              "timedOut": null,
              "duration": 612,
              "state": "passed",
              "speed": "fast",
              "pass": true,
              "fail": false,
              "pending": false,
              "context": null,
              "code": "NEW_USER.newUser.click();\nCOMM_ELEMENTS.passwordStrength('weak');",
              "err": {},
              "uuid": "4d8fa688-fb6e-4c64-8d1b-d93c0b1a9066",
              "parentUUID": "eed1b4cd-40a8-4389-a607-4b0bd1e0baf7",
              "isHook": false,
              "skipped": false
            },
            {
              "title": "Create account : Validate Password Strength - fair",
              "fullTitle": "EVA MD : Add New Managers - Registration codes Create account : Validate Password Strength - fair",
              "timedOut": null,
              "duration": 782,
              "state": "passed",
              "speed": "fast",
              "pass": true,
              "fail": false,
              "pending": false,
              "context": null,
              "code": "NEW_USER.newUser.click();\nCOMM_ELEMENTS.passwordStrength('fair');",
              "err": {},
              "uuid": "f33f3bf0-55e3-4e19-abe4-d90ca37f4824",
              "parentUUID": "eed1b4cd-40a8-4389-a607-4b0bd1e0baf7",
              "isHook": false,
              "skipped": false
            },
            {
              "title": "Create account : Validate Password Strength - good",
              "fullTitle": "EVA MD : Add New Managers - Registration codes Create account : Validate Password Strength - good",
              "timedOut": null,
              "duration": 705,
              "state": "passed",
              "speed": "fast",
              "pass": true,
              "fail": false,
              "pending": false,
              "context": null,
              "code": "NEW_USER.newUser.click();\nCOMM_ELEMENTS.passwordStrength('good');",
              "err": {},
              "uuid": "30d66bb0-8d59-4be5-b86f-b53c6d896735",
              "parentUUID": "eed1b4cd-40a8-4389-a607-4b0bd1e0baf7",
              "isHook": false,
              "skipped": false
            },
            {
              "title": "Create account : Validate Password Strength - strong",
              "fullTitle": "EVA MD : Add New Managers - Registration codes Create account : Validate Password Strength - strong",
              "timedOut": null,
              "duration": 868,
              "state": "passed",
              "speed": "fast",
              "pass": true,
              "fail": false,
              "pending": false,
              "context": null,
              "code": "NEW_USER.newUser.click();\nCOMM_ELEMENTS.passwordStrength('strong');",
              "err": {},
              "uuid": "44817128-749c-4e6b-81b9-77b259e67ce4",
              "parentUUID": "eed1b4cd-40a8-4389-a607-4b0bd1e0baf7",
              "isHook": false,
              "skipped": false
            }
          ],
          "suites": [],
          "passes": [
            "eb7b6d80-1ab4-47a6-b8a1-1c4686dd2226",
            "18ad9a9b-c89a-46ec-b172-ead449a188e3",
            "0883a395-3abd-4b6d-b2b6-c6fd7d85f3da",
            "fa6c5de4-2de0-4628-abac-7f746d4d5689",
            "7763df55-e9d8-48e0-a153-e3d4642e053f",
            "b463a845-3203-45d5-95df-42cc0da719cc",
            "c6661eb8-b05e-49c8-a4b3-21c70b1450b8",
            "d20bd169-083f-45e3-867b-6fc2ca17604a",
            "4d8fa688-fb6e-4c64-8d1b-d93c0b1a9066",
            "f33f3bf0-55e3-4e19-abe4-d90ca37f4824",
            "30d66bb0-8d59-4be5-b86f-b53c6d896735",
            "44817128-749c-4e6b-81b9-77b259e67ce4"
          ],
          "failures": [],
          "pending": [],
          "skipped": [],
          "duration": 43384,
          "root": false,
          "rootEmpty": false,
          "_timeout": 2000
        }
      ],
      "passes": [],
      "failures": [],
      "pending": [],
      "skipped": [],
      "duration": 0,
      "root": true,
      "rootEmpty": true,
      "_timeout": 2000
    },
    {
      "uuid": "ee9cd097-9362-4eb3-88fe-1ce051af24a3",
      "title": "",
      "fullFile": "cypress\\e2e\\eva-md\\manager-admin\\contact_us.ts",
      "file": "cypress\\e2e\\eva-md\\manager-admin\\contact_us.ts",
      "beforeHooks": [],
      "afterHooks": [],
      "tests": [],
      "suites": [
        {
          "uuid": "7d6f00d6-ba63-457f-9401-1403d011c36f",
          "title": "EVA MD : Contact Us - Manager Admin",
          "fullFile": "",
          "file": "",
          "beforeHooks": [],
          "afterHooks": [],
          "tests": [
            {
              "title": "Default items should visible",
              "fullTitle": "EVA MD : Contact Us - Manager Admin Default items should visible",
              "timedOut": null,
              "duration": 28959,
              "state": "passed",
              "speed": "slow",
              "pass": true,
              "fail": false,
              "pending": false,
              "context": null,
              "code": "CONTACT_US.verifyItemsIfExist();\nFOOTER.verifyItemsIfExist('EVA_MD');\nHEADER.verifyItemsIfExist('MA');",
              "err": {},
              "uuid": "7fa87453-1706-4e6e-b998-d5b775470101",
              "parentUUID": "7d6f00d6-ba63-457f-9401-1403d011c36f",
              "isHook": false,
              "skipped": false
            },
            {
              "title": "Check texts/labels if visible",
              "fullTitle": "EVA MD : Contact Us - Manager Admin Check texts/labels if visible",
              "timedOut": null,
              "duration": 2752,
              "state": "passed",
              "speed": "fast",
              "pass": true,
              "fail": false,
              "pending": false,
              "context": null,
              "code": "CONTACT_US.verifyTextsIfContains();\nFOOTER.verifyTextsIfContains('', 'EVA_MD');\nHEADER.verifyTextsIfContains();",
              "err": {},
              "uuid": "298ad096-7441-4fb2-a503-3de33accffda",
              "parentUUID": "7d6f00d6-ba63-457f-9401-1403d011c36f",
              "isHook": false,
              "skipped": false
            },
            {
              "title": "Validate Cancel submission",
              "fullTitle": "EVA MD : Contact Us - Manager Admin Validate Cancel submission",
              "timedOut": null,
              "duration": 4588,
              "state": "passed",
              "speed": "fast",
              "pass": true,
              "fail": false,
              "pending": false,
              "context": null,
              "code": "CONTACT_US.cancelSubmission();",
              "err": {},
              "uuid": "22214c3d-5bce-4392-8804-518a84a370b1",
              "parentUUID": "7d6f00d6-ba63-457f-9401-1403d011c36f",
              "isHook": false,
              "skipped": false
            },
            {
              "title": "Validate contact-us submission",
              "fullTitle": "EVA MD : Contact Us - Manager Admin Validate contact-us submission",
              "timedOut": null,
              "duration": 10894,
              "state": "passed",
              "speed": "slow",
              "pass": true,
              "fail": false,
              "pending": false,
              "context": null,
              "code": "SIDE_NAV_BAR.editProfile();\nCONTACT_US.viewContactUsTab();\nCONTACT_US.submitContactUs();",
              "err": {},
              "uuid": "26221be1-114e-442e-858c-f7d641fd9c7b",
              "parentUUID": "7d6f00d6-ba63-457f-9401-1403d011c36f",
              "isHook": false,
              "skipped": false
            }
          ],
          "suites": [],
          "passes": [
            "7fa87453-1706-4e6e-b998-d5b775470101",
            "298ad096-7441-4fb2-a503-3de33accffda",
            "22214c3d-5bce-4392-8804-518a84a370b1",
            "26221be1-114e-442e-858c-f7d641fd9c7b"
          ],
          "failures": [],
          "pending": [],
          "skipped": [],
          "duration": 47193,
          "root": false,
          "rootEmpty": false,
          "_timeout": 2000
        }
      ],
      "passes": [],
      "failures": [],
      "pending": [],
      "skipped": [],
      "duration": 0,
      "root": true,
      "rootEmpty": true,
      "_timeout": 2000
    }
  ],
  "meta": {
    "mocha": {
      "version": "7.0.1"
    },
    "mochawesome": {
      "options": {
        "quiet": false,
        "reportFilename": "mochawesome",
        "saveHtml": false,
        "saveJson": true,
        "consoleReporter": "spec",
        "useInlineDiffs": false,
        "code": true
      },
      "version": "7.1.3"
    },
    "marge": {
      "options": {
        "id": "default",
        "reportDir": "cypress/reports/mocha",
        "quite": true,
        "overwrite": false,
        "html": false,
        "json": true
      },
      "version": "6.2.0"
    }
  }
}